{
  "2023-12-22": {
    "numLegs": 17,
    "numLegsLast": 0,
    "totalLegs": 17,
    "legsWon": 2,
    "soloGame": 0,
    "average": {
      "dartsThrown": 499,
      "average": 27.11422845691383,
      "first9Average": 39.13725490196079,
      "checkouts": 110,
      "checkoutPoints": 16,
      "less60": 155,
      "plus60": 12,
      "plus100": 0,
      "plus140": 0,
      "total180": 0,
      "score": 0,
      "first9Score": 0,
      "checkoutsHit": 110,
      "checkoutPercent": 0.01818181818181818,
      "checkoutPointsAverage": 1.1176470588235294
    },
    "averageLast": {
      "dartsThrown": 0,
      "average": 0,
      "first9Average": 0,
      "checkouts": 0,
      "checkoutPoints": 0,
      "less60": 0,
      "plus60": 0,
      "plus100": 0,
      "plus140": 0,
      "total180": 0,
      "score": 0,
      "first9Score": 0,
      "checkoutsHit": 0,
      "checkoutPercent": 0,
      "checkoutPointsAverage": 0
    },
    "best": {
      "dartsThrown": 499,
      "average": 47,
      "first9Average": 53.66666666666667,
      "checkouts": 0,
      "checkoutPoints": 16,
      "less60": 9.117647058823529,
      "plus60": 0.7058823529411765,
      "plus100": 0,
      "plus140": 0,
      "total180": 0,
      "score": 0,
      "first9Score": 0,
      "checkoutsHit": 110,
      "checkoutPercent": 0,
      "checkoutPointsAverage": 1.1176470588235294
    },
    "bestLast": {
      "dartsThrown": 0,
      "average": 0,
      "first9Average": 0,
      "checkouts": 0,
      "checkoutPoints": 0,
      "less60": 0,
      "plus60": 0,
      "plus100": 0,
      "plus140": 0,
      "total180": 0,
      "score": 0,
      "first9Score": 0,
      "checkoutsHit": 0,
      "checkoutPercent": 0,
      "checkoutPointsAverage": 0
    }
  },
  "2023-12-26": {
    "numLegs": 17,
    "numLegsLast": 0,
    "totalLegs": 17,
    "legsWon": 2,
    "soloGame": 0,
    "average": {
      "dartsThrown": 499,
      "average": 27.11422845691383,
      "first9Average": 39.13725490196079,
      "checkouts": 110,
      "checkoutPoints": 16,
      "less60": 155,
      "plus60": 12,
      "plus100": 0,
      "plus140": 0,
      "total180": 0,
      "score": 0,
      "first9Score": 0,
      "checkoutsHit": 110,
      "checkoutPercent": 0.01818181818181818,
      "checkoutPointsAverage": 1.1176470588235294
    },
    "averageLast": {
      "dartsThrown": 0,
      "average": 0,
      "first9Average": 0,
      "checkouts": 0,
      "checkoutPoints": 0,
      "less60": 0,
      "plus60": 0,
      "plus100": 0,
      "plus140": 0,
      "total180": 0,
      "score": 0,
      "first9Score": 0,
      "checkoutsHit": 0,
      "checkoutPercent": 0,
      "checkoutPointsAverage": 0
    },
    "best": {
      "dartsThrown": 499,
      "average": 47,
      "first9Average": 53.66666666666667,
      "checkouts": 0,
      "checkoutPoints": 16,
      "less60": 9.117647058823529,
      "plus60": 0.7058823529411765,
      "plus100": 0,
      "plus140": 0,
      "total180": 0,
      "score": 0,
      "first9Score": 0,
      "checkoutsHit": 110,
      "checkoutPercent": 0,
      "checkoutPointsAverage": 1.1176470588235294
    },
    "bestLast": {
      "dartsThrown": 0,
      "average": 0,
      "first9Average": 0,
      "checkouts": 0,
      "checkoutPoints": 0,
      "less60": 0,
      "plus60": 0,
      "plus100": 0,
      "plus140": 0,
      "total180": 0,
      "score": 0,
      "first9Score": 0,
      "checkoutsHit": 0,
      "checkoutPercent": 0,
      "checkoutPointsAverage": 0
    }
  },
  "2023-12-27": {
    "numLegs": 17,
    "numLegsLast": 0,
    "totalLegs": 17,
    "legsWon": 2,
    "soloGame": 0,
    "average": {
      "dartsThrown": 499,
      "average": 27.11422845691383,
      "first9Average": 39.13725490196079,
      "checkouts": 110,
      "checkoutPoints": 16,
      "less60": 155,
      "plus60": 12,
      "plus100": 0,
      "plus140": 0,
      "total180": 0,
      "score": 0,
      "first9Score": 0,
      "checkoutsHit": 110,
      "checkoutPercent": 0.01818181818181818,
      "checkoutPointsAverage": 1.1176470588235294
    },
    "averageLast": {
      "dartsThrown": 0,
      "average": 0,
      "first9Average": 0,
      "checkouts": 0,
      "checkoutPoints": 0,
      "less60": 0,
      "plus60": 0,
      "plus100": 0,
      "plus140": 0,
      "total180": 0,
      "score": 0,
      "first9Score": 0,
      "checkoutsHit": 0,
      "checkoutPercent": 0,
      "checkoutPointsAverage": 0
    },
    "best": {
      "dartsThrown": 499,
      "average": 47,
      "first9Average": 53.66666666666667,
      "checkouts": 0,
      "checkoutPoints": 16,
      "less60": 9.117647058823529,
      "plus60": 0.7058823529411765,
      "plus100": 0,
      "plus140": 0,
      "total180": 0,
      "score": 0,
      "first9Score": 0,
      "checkoutsHit": 110,
      "checkoutPercent": 0,
      "checkoutPointsAverage": 1.1176470588235294
    },
    "bestLast": {
      "dartsThrown": 0,
      "average": 0,
      "first9Average": 0,
      "checkouts": 0,
      "checkoutPoints": 0,
      "less60": 0,
      "plus60": 0,
      "plus100": 0,
      "plus140": 0,
      "total180": 0,
      "score": 0,
      "first9Score": 0,
      "checkoutsHit": 0,
      "checkoutPercent": 0,
      "checkoutPointsAverage": 0
    }
  },
  "2023-12-28": {
    "numLegs": 17,
    "numLegsLast": 0,
    "totalLegs": 17,
    "legsWon": 2,
    "soloGame": 0,
    "average": {
      "dartsThrown": 499,
      "average": 27.11422845691383,
      "first9Average": 39.13725490196079,
      "checkouts": 110,
      "checkoutPoints": 16,
      "less60": 155,
      "plus60": 12,
      "plus100": 0,
      "plus140": 0,
      "total180": 0,
      "score": 0,
      "first9Score": 0,
      "checkoutsHit": 110,
      "checkoutPercent": 0.01818181818181818,
      "checkoutPointsAverage": 1.1176470588235294
    },
    "averageLast": {
      "dartsThrown": 0,
      "average": 0,
      "first9Average": 0,
      "checkouts": 0,
      "checkoutPoints": 0,
      "less60": 0,
      "plus60": 0,
      "plus100": 0,
      "plus140": 0,
      "total180": 0,
      "score": 0,
      "first9Score": 0,
      "checkoutsHit": 0,
      "checkoutPercent": 0,
      "checkoutPointsAverage": 0
    },
    "best": {
      "dartsThrown": 499,
      "average": 47,
      "first9Average": 53.66666666666667,
      "checkouts": 0,
      "checkoutPoints": 16,
      "less60": 9.117647058823529,
      "plus60": 0.7058823529411765,
      "plus100": 0,
      "plus140": 0,
      "total180": 0,
      "score": 0,
      "first9Score": 0,
      "checkoutsHit": 110,
      "checkoutPercent": 0,
      "checkoutPointsAverage": 1.1176470588235294
    },
    "bestLast": {
      "dartsThrown": 0,
      "average": 0,
      "first9Average": 0,
      "checkouts": 0,
      "checkoutPoints": 0,
      "less60": 0,
      "plus60": 0,
      "plus100": 0,
      "plus140": 0,
      "total180": 0,
      "score": 0,
      "first9Score": 0,
      "checkoutsHit": 0,
      "checkoutPercent": 0,
      "checkoutPointsAverage": 0
    }
  },
  "2023-12-29": {
    "numLegs": 17,
    "numLegsLast": 0,
    "totalLegs": 17,
    "legsWon": 2,
    "soloGame": 0,
    "average": {
      "dartsThrown": 499,
      "average": 27.11422845691383,
      "first9Average": 39.13725490196079,
      "checkouts": 110,
      "checkoutPoints": 16,
      "less60": 155,
      "plus60": 12,
      "plus100": 0,
      "plus140": 0,
      "total180": 0,
      "score": 0,
      "first9Score": 0,
      "checkoutsHit": 110,
      "checkoutPercent": 0.01818181818181818,
      "checkoutPointsAverage": 1.1176470588235294
    },
    "averageLast": {
      "dartsThrown": 0,
      "average": 0,
      "first9Average": 0,
      "checkouts": 0,
      "checkoutPoints": 0,
      "less60": 0,
      "plus60": 0,
      "plus100": 0,
      "plus140": 0,
      "total180": 0,
      "score": 0,
      "first9Score": 0,
      "checkoutsHit": 0,
      "checkoutPercent": 0,
      "checkoutPointsAverage": 0
    },
    "best": {
      "dartsThrown": 499,
      "average": 47,
      "first9Average": 53.66666666666667,
      "checkouts": 0,
      "checkoutPoints": 16,
      "less60": 9.117647058823529,
      "plus60": 0.7058823529411765,
      "plus100": 0,
      "plus140": 0,
      "total180": 0,
      "score": 0,
      "first9Score": 0,
      "checkoutsHit": 110,
      "checkoutPercent": 0,
      "checkoutPointsAverage": 1.1176470588235294
    },
    "bestLast": {
      "dartsThrown": 0,
      "average": 0,
      "first9Average": 0,
      "checkouts": 0,
      "checkoutPoints": 0,
      "less60": 0,
      "plus60": 0,
      "plus100": 0,
      "plus140": 0,
      "total180": 0,
      "score": 0,
      "first9Score": 0,
      "checkoutsHit": 0,
      "checkoutPercent": 0,
      "checkoutPointsAverage": 0
    }
  },
  "2023-12-30": {
    "numLegs": 17,
    "numLegsLast": 0,
    "totalLegs": 17,
    "legsWon": 2,
    "soloGame": 0,
    "average": {
      "dartsThrown": 499,
      "average": 27.11422845691383,
      "first9Average": 39.13725490196079,
      "checkouts": 110,
      "checkoutPoints": 16,
      "less60": 155,
      "plus60": 12,
      "plus100": 0,
      "plus140": 0,
      "total180": 0,
      "score": 0,
      "first9Score": 0,
      "checkoutsHit": 110,
      "checkoutPercent": 0.01818181818181818,
      "checkoutPointsAverage": 1.1176470588235294
    },
    "averageLast": {
      "dartsThrown": 0,
      "average": 0,
      "first9Average": 0,
      "checkouts": 0,
      "checkoutPoints": 0,
      "less60": 0,
      "plus60": 0,
      "plus100": 0,
      "plus140": 0,
      "total180": 0,
      "score": 0,
      "first9Score": 0,
      "checkoutsHit": 0,
      "checkoutPercent": 0,
      "checkoutPointsAverage": 0
    },
    "best": {
      "dartsThrown": 499,
      "average": 47,
      "first9Average": 53.66666666666667,
      "checkouts": 0,
      "checkoutPoints": 16,
      "less60": 9.117647058823529,
      "plus60": 0.7058823529411765,
      "plus100": 0,
      "plus140": 0,
      "total180": 0,
      "score": 0,
      "first9Score": 0,
      "checkoutsHit": 110,
      "checkoutPercent": 0,
      "checkoutPointsAverage": 1.1176470588235294
    },
    "bestLast": {
      "dartsThrown": 0,
      "average": 0,
      "first9Average": 0,
      "checkouts": 0,
      "checkoutPoints": 0,
      "less60": 0,
      "plus60": 0,
      "plus100": 0,
      "plus140": 0,
      "total180": 0,
      "score": 0,
      "first9Score": 0,
      "checkoutsHit": 0,
      "checkoutPercent": 0,
      "checkoutPointsAverage": 0
    }
  },
  "2024-01-08": {
    "numLegs": 17,
    "numLegsLast": 0,
    "totalLegs": 17,
    "legsWon": 2,
    "soloGame": 0,
    "average": {
      "dartsThrown": 499,
      "average": 27.11422845691383,
      "first9Average": 39.13725490196079,
      "checkouts": 110,
      "checkoutPoints": 16,
      "less60": 155,
      "plus60": 12,
      "plus100": 0,
      "plus140": 0,
      "total180": 0,
      "score": 0,
      "first9Score": 0,
      "checkoutsHit": 110,
      "checkoutPercent": 0.01818181818181818,
      "checkoutPointsAverage": 1.1176470588235294
    },
    "averageLast": {
      "dartsThrown": 0,
      "average": 0,
      "first9Average": 0,
      "checkouts": 0,
      "checkoutPoints": 0,
      "less60": 0,
      "plus60": 0,
      "plus100": 0,
      "plus140": 0,
      "total180": 0,
      "score": 0,
      "first9Score": 0,
      "checkoutsHit": 0,
      "checkoutPercent": 0,
      "checkoutPointsAverage": 0
    },
    "best": {
      "dartsThrown": 499,
      "average": 47,
      "first9Average": 53.66666666666667,
      "checkouts": 0,
      "checkoutPoints": 16,
      "less60": 9.117647058823529,
      "plus60": 0.7058823529411765,
      "plus100": 0,
      "plus140": 0,
      "total180": 0,
      "score": 0,
      "first9Score": 0,
      "checkoutsHit": 110,
      "checkoutPercent": 0,
      "checkoutPointsAverage": 1.1176470588235294
    },
    "bestLast": {
      "dartsThrown": 0,
      "average": 0,
      "first9Average": 0,
      "checkouts": 0,
      "checkoutPoints": 0,
      "less60": 0,
      "plus60": 0,
      "plus100": 0,
      "plus140": 0,
      "total180": 0,
      "score": 0,
      "first9Score": 0,
      "checkoutsHit": 0,
      "checkoutPercent": 0,
      "checkoutPointsAverage": 0
    }
  },
  "2024-01-10": {
    "numLegs": 19,
    "numLegsLast": 0,
    "totalLegs": 19,
    "legsWon": 2,
    "soloGame": 0,
    "average": {
      "dartsThrown": 532,
      "average": 27.82894736842105,
      "first9Average": 38.771929824561404,
      "checkouts": 110,
      "checkoutPoints": 16,
      "less60": 164,
      "plus60": 14,
      "plus100": 0,
      "plus140": 0,
      "total180": 0,
      "score": 0,
      "first9Score": 0,
      "checkoutsHit": 110,
      "checkoutPercent": 0.01818181818181818,
      "checkoutPointsAverage": 1
    },
    "averageLast": {
      "dartsThrown": 0,
      "average": 0,
      "first9Average": 0,
      "checkouts": 0,
      "checkoutPoints": 0,
      "less60": 0,
      "plus60": 0,
      "plus100": 0,
      "plus140": 0,
      "total180": 0,
      "score": 0,
      "first9Score": 0,
      "checkoutsHit": 0,
      "checkoutPercent": 0,
      "checkoutPointsAverage": 0
    },
    "best": {
      "dartsThrown": 532,
      "average": 47,
      "first9Average": 53.66666666666667,
      "checkouts": 0,
      "checkoutPoints": 16,
      "less60": 8.631578947368421,
      "plus60": 0.7368421052631579,
      "plus100": 0,
      "plus140": 0,
      "total180": 0,
      "score": 0,
      "first9Score": 0,
      "checkoutsHit": 110,
      "checkoutPercent": 0,
      "checkoutPointsAverage": 1
    },
    "bestLast": {
      "dartsThrown": 0,
      "average": 0,
      "first9Average": 0,
      "checkouts": 0,
      "checkoutPoints": 0,
      "less60": 0,
      "plus60": 0,
      "plus100": 0,
      "plus140": 0,
      "total180": 0,
      "score": 0,
      "first9Score": 0,
      "checkoutsHit": 0,
      "checkoutPercent": 0,
      "checkoutPointsAverage": 0
    }
  },
  "2024-01-11": {
    "numLegs": 19,
    "numLegsLast": 0,
    "totalLegs": 19,
    "legsWon": 2,
    "soloGame": 0,
    "average": {
      "dartsThrown": 532,
      "average": 27.82894736842105,
      "first9Average": 38.771929824561404,
      "checkouts": 110,
      "checkoutPoints": 16,
      "less60": 164,
      "plus60": 14,
      "plus100": 0,
      "plus140": 0,
      "total180": 0,
      "score": 0,
      "first9Score": 0,
      "checkoutsHit": 110,
      "checkoutPercent": 0.01818181818181818,
      "checkoutPointsAverage": 1
    },
    "averageLast": {
      "dartsThrown": 0,
      "average": 0,
      "first9Average": 0,
      "checkouts": 0,
      "checkoutPoints": 0,
      "less60": 0,
      "plus60": 0,
      "plus100": 0,
      "plus140": 0,
      "total180": 0,
      "score": 0,
      "first9Score": 0,
      "checkoutsHit": 0,
      "checkoutPercent": 0,
      "checkoutPointsAverage": 0
    },
    "best": {
      "dartsThrown": 532,
      "average": 47,
      "first9Average": 53.66666666666667,
      "checkouts": 0,
      "checkoutPoints": 16,
      "less60": 8.631578947368421,
      "plus60": 0.7368421052631579,
      "plus100": 0,
      "plus140": 0,
      "total180": 0,
      "score": 0,
      "first9Score": 0,
      "checkoutsHit": 110,
      "checkoutPercent": 0,
      "checkoutPointsAverage": 1
    },
    "bestLast": {
      "dartsThrown": 0,
      "average": 0,
      "first9Average": 0,
      "checkouts": 0,
      "checkoutPoints": 0,
      "less60": 0,
      "plus60": 0,
      "plus100": 0,
      "plus140": 0,
      "total180": 0,
      "score": 0,
      "first9Score": 0,
      "checkoutsHit": 0,
      "checkoutPercent": 0,
      "checkoutPointsAverage": 0
    }
  },
  "2024-01-12": {
    "numLegs": 22,
    "numLegsLast": 0,
    "totalLegs": 22,
    "legsWon": 2,
    "soloGame": 0,
    "average": {
      "dartsThrown": 592,
      "average": 29.929054054054053,
      "first9Average": 40.515151515151516,
      "checkouts": 112,
      "checkoutPoints": 16,
      "less60": 180,
      "plus60": 16,
      "plus100": 1,
      "plus140": 1,
      "total180": 0,
      "score": 0,
      "first9Score": 0,
      "checkoutsHit": 112,
      "checkoutPercent": 0.017857142857142856,
      "checkoutPointsAverage": 0.8636363636363636
    },
    "averageLast": {
      "dartsThrown": 0,
      "average": 0,
      "first9Average": 0,
      "checkouts": 0,
      "checkoutPoints": 0,
      "less60": 0,
      "plus60": 0,
      "plus100": 0,
      "plus140": 0,
      "total180": 0,
      "score": 0,
      "first9Score": 0,
      "checkoutsHit": 0,
      "checkoutPercent": 0,
      "checkoutPointsAverage": 0
    },
    "best": {
      "dartsThrown": 592,
      "average": 87,
      "first9Average": 87,
      "checkouts": 0,
      "checkoutPoints": 16,
      "less60": 8.181818181818182,
      "plus60": 0.7272727272727273,
      "plus100": 0.045454545454545456,
      "plus140": 0.045454545454545456,
      "total180": 0,
      "score": 0,
      "first9Score": 0,
      "checkoutsHit": 112,
      "checkoutPercent": 0,
      "checkoutPointsAverage": 0.8636363636363636
    },
    "bestLast": {
      "dartsThrown": 0,
      "average": 0,
      "first9Average": 0,
      "checkouts": 0,
      "checkoutPoints": 0,
      "less60": 0,
      "plus60": 0,
      "plus100": 0,
      "plus140": 0,
      "total180": 0,
      "score": 0,
      "first9Score": 0,
      "checkoutsHit": 0,
      "checkoutPercent": 0,
      "checkoutPointsAverage": 0
    }
  },
  "2024-01-15": {
    "numLegs": 24,
    "numLegsLast": 0,
    "totalLegs": 24,
    "legsWon": 2,
    "soloGame": 0,
    "average": {
      "dartsThrown": 640,
      "average": 30.1078125,
      "first9Average": 40.25,
      "checkouts": 117,
      "checkoutPoints": 16,
      "less60": 196,
      "plus60": 16,
      "plus100": 1,
      "plus140": 1,
      "total180": 0,
      "score": 0,
      "first9Score": 0,
      "checkoutsHit": 117,
      "checkoutPercent": 0.017094017094017096,
      "checkoutPointsAverage": 0.7916666666666666
    },
    "averageLast": {
      "dartsThrown": 0,
      "average": 0,
      "first9Average": 0,
      "checkouts": 0,
      "checkoutPoints": 0,
      "less60": 0,
      "plus60": 0,
      "plus100": 0,
      "plus140": 0,
      "total180": 0,
      "score": 0,
      "first9Score": 0,
      "checkoutsHit": 0,
      "checkoutPercent": 0,
      "checkoutPointsAverage": 0
    },
    "best": {
      "dartsThrown": 640,
      "average": 87,
      "first9Average": 87,
      "checkouts": 0,
      "checkoutPoints": 16,
      "less60": 8.166666666666666,
      "plus60": 0.6666666666666666,
      "plus100": 0.041666666666666664,
      "plus140": 0.041666666666666664,
      "total180": 0,
      "score": 0,
      "first9Score": 0,
      "checkoutsHit": 117,
      "checkoutPercent": 0,
      "checkoutPointsAverage": 0.7916666666666666
    },
    "bestLast": {
      "dartsThrown": 0,
      "average": 0,
      "first9Average": 0,
      "checkouts": 0,
      "checkoutPoints": 0,
      "less60": 0,
      "plus60": 0,
      "plus100": 0,
      "plus140": 0,
      "total180": 0,
      "score": 0,
      "first9Score": 0,
      "checkoutsHit": 0,
      "checkoutPercent": 0,
      "checkoutPointsAverage": 0
    }
  },
  "2024-01-16": {
    "numLegs": 24,
    "numLegsLast": 0,
    "totalLegs": 24,
    "legsWon": 2,
    "soloGame": 0,
    "average": {
      "dartsThrown": 640,
      "average": 30.1078125,
      "first9Average": 40.25,
      "checkouts": 117,
      "checkoutPoints": 16,
      "less60": 196,
      "plus60": 16,
      "plus100": 1,
      "plus140": 1,
      "total180": 0,
      "score": 0,
      "first9Score": 0,
      "checkoutsHit": 117,
      "checkoutPercent": 0.017094017094017096,
      "checkoutPointsAverage": 0.7916666666666666
    },
    "averageLast": {
      "dartsThrown": 0,
      "average": 0,
      "first9Average": 0,
      "checkouts": 0,
      "checkoutPoints": 0,
      "less60": 0,
      "plus60": 0,
      "plus100": 0,
      "plus140": 0,
      "total180": 0,
      "score": 0,
      "first9Score": 0,
      "checkoutsHit": 0,
      "checkoutPercent": 0,
      "checkoutPointsAverage": 0
    },
    "best": {
      "dartsThrown": 640,
      "average": 87,
      "first9Average": 87,
      "checkouts": 0,
      "checkoutPoints": 16,
      "less60": 8.166666666666666,
      "plus60": 0.6666666666666666,
      "plus100": 0.041666666666666664,
      "plus140": 0.041666666666666664,
      "total180": 0,
      "score": 0,
      "first9Score": 0,
      "checkoutsHit": 117,
      "checkoutPercent": 0,
      "checkoutPointsAverage": 0.7916666666666666
    },
    "bestLast": {
      "dartsThrown": 0,
      "average": 0,
      "first9Average": 0,
      "checkouts": 0,
      "checkoutPoints": 0,
      "less60": 0,
      "plus60": 0,
      "plus100": 0,
      "plus140": 0,
      "total180": 0,
      "score": 0,
      "first9Score": 0,
      "checkoutsHit": 0,
      "checkoutPercent": 0,
      "checkoutPointsAverage": 0
    }
  },
  "2024-01-17": {
    "numLegs": 27,
    "numLegsLast": 0,
    "totalLegs": 27,
    "legsWon": 2,
    "soloGame": 0,
    "average": {
      "dartsThrown": 697,
      "average": 30.46054519368723,
      "first9Average": 40.44444444444444,
      "checkouts": 117,
      "checkoutPoints": 16,
      "less60": 214,
      "plus60": 17,
      "plus100": 1,
      "plus140": 1,
      "total180": 0,
      "score": 0,
      "first9Score": 0,
      "checkoutsHit": 117,
      "checkoutPercent": 0.017094017094017096,
      "checkoutPointsAverage": 0.7037037037037037
    },
    "averageLast": {
      "dartsThrown": 0,
      "average": 0,
      "first9Average": 0,
      "checkouts": 0,
      "checkoutPoints": 0,
      "less60": 0,
      "plus60": 0,
      "plus100": 0,
      "plus140": 0,
      "total180": 0,
      "score": 0,
      "first9Score": 0,
      "checkoutsHit": 0,
      "checkoutPercent": 0,
      "checkoutPointsAverage": 0
    },
    "best": {
      "dartsThrown": 697,
      "average": 87,
      "first9Average": 87,
      "checkouts": 0,
      "checkoutPoints": 16,
      "less60": 7.925925925925926,
      "plus60": 0.6296296296296297,
      "plus100": 0.037037037037037035,
      "plus140": 0.037037037037037035,
      "total180": 0,
      "score": 0,
      "first9Score": 0,
      "checkoutsHit": 117,
      "checkoutPercent": 0,
      "checkoutPointsAverage": 0.7037037037037037
    },
    "bestLast": {
      "dartsThrown": 0,
      "average": 0,
      "first9Average": 0,
      "checkouts": 0,
      "checkoutPoints": 0,
      "less60": 0,
      "plus60": 0,
      "plus100": 0,
      "plus140": 0,
      "total180": 0,
      "score": 0,
      "first9Score": 0,
      "checkoutsHit": 0,
      "checkoutPercent": 0,
      "checkoutPointsAverage": 0
    }
  }
}